setup.py
distributions/Binomialdistribution.py
distributions/Gaussiandistribution.py
distributions/Generaldistribution.py
distributions/__init__.py
test_package2020.egg-info/PKG-INFO
test_package2020.egg-info/SOURCES.txt
test_package2020.egg-info/dependency_links.txt
test_package2020.egg-info/not-zip-safe
test_package2020.egg-info/top_level.txt